var carolinahall = {
"type": "FeatureCollection",
"crs": { "type": "name", "properties": { "name": "urn:ogc:def:crs:OGC:1.3:CRS84" } },
"features": [
{ "type": "Feature", "properties": { "id": 1, "descrip": "Carolina Hall" }, "geometry": { "type": "Point", "coordinates": [ -79.049935, 35.911269 ] } }
]
}